llm_xai.py
llm_xai-0.2.dist-info/LICENSE
llm_xai-0.2.dist-info/METADATA
llm_xai-0.2.dist-info/WHEEL
llm_xai-0.2.dist-info/entry_points.txt
llm_xai-0.2.dist-info/top_level.txt
llm_xai-0.2.dist-info/RECORD
