Metadata-Version: 2.1
Name: llm-xai
Version: 0.2
Summary: LLM plugin for models hosted by OpenRouter
Author: Nick Mystic
License: Apache-2.0
Project-URL: Homepage, https://github.com/ghostofpokemon/llm-xai
Project-URL: Changelog, https://github.com/ghostofpokemon/llm-xai/releases
Project-URL: Issues, https://github.com/ghostofpokemon/llm-xai/issues
Project-URL: CI, https://github.com/ghostofpokemon/llm-xai/actions
Classifier: License :: OSI Approved :: Apache Software License
License-File: LICENSE
Requires-Dist: llm >=0.8
Requires-Dist: httpx
Provides-Extra: test
Requires-Dist: pytest ; extra == 'test'
Requires-Dist: pytest-httpx ; extra == 'test'
